<?xml version="1.0" encoding="UTF-8"?>

<!-- in this routing file acquisition is actually the productType. Reason 
	is the configuration in the corresponding application.yml -->

<level_products_routing>
	<!-- Satellite A -->

	<level_products_route>
		<level_products_from>
			<acquisition>DO_0_DOP__G</acquisition>
			<satellite_id>A</satellite_id>
		</level_products_from>
		<level_products_to>
			<task_tables>
				<task_table>TaskTable_S3A_L0_DO_DOP_06_12.xml</task_table>
			</task_tables>
		</level_products_to>
	</level_products_route>
	
	<level_products_route>
		<level_products_from>
			<acquisition>DO_0_NAV__G</acquisition>
			<satellite_id>A</satellite_id>
		</level_products_from>
		<level_products_to>
			<task_tables>
				<task_table>TaskTable_S3A_L0_DO_NAV_06_12.xml</task_table>
			</task_tables>
		</level_products_to>
	</level_products_route>
	
	<level_products_route>
		<level_products_from>
			<acquisition>GN_0_GNS__G</acquisition>
			<satellite_id>A</satellite_id>
		</level_products_from>
		<level_products_to>
			<task_tables>
				<task_table>TaskTable_S3A_L0_GN_GNS_06_12.xml</task_table>
			</task_tables>
		</level_products_to>
	</level_products_route>
	
	<level_products_route>
		<level_products_from>
			<acquisition>MW_0_MWR__G</acquisition>
			<satellite_id>A</satellite_id>
		</level_products_from>
		<level_products_to>
			<task_tables>
				<task_table>TaskTable_S3A_L0_MW_MWR_06_12.xml</task_table>
			</task_tables>
		</level_products_to>
	</level_products_route>
	
	<level_products_route>
		<level_products_from>
			<acquisition>OL_0_CR___G</acquisition>
			<satellite_id>A</satellite_id>
		</level_products_from>
		<level_products_to>
			<task_tables>
				<task_table>TaskTable_S3A_L0_OL_CR__06_12.xml</task_table>
			</task_tables>
		</level_products_to>
	</level_products_route>
	
	<level_products_route>
		<level_products_from>
			<acquisition>OL_0_EFR__G</acquisition>
			<satellite_id>A</satellite_id>
		</level_products_from>
		<level_products_to>
			<task_tables>
				<task_table>TaskTable_S3A_L0_OL_EFR_06_12.xml</task_table>
			</task_tables>
		</level_products_to>
	</level_products_route>
	
	<level_products_route>
		<level_products_from>
			<acquisition>SL_0_SLT__G</acquisition>
			<satellite_id>A</satellite_id>
		</level_products_from>
		<level_products_to>
			<task_tables>
				<task_table>TaskTable_S3A_L0_SL_SLT_06_12.xml</task_table>
			</task_tables>
		</level_products_to>
	</level_products_route>
	
	<level_products_route>
		<level_products_from>
			<acquisition>SR_0_CAL__G</acquisition>
			<satellite_id>A</satellite_id>
		</level_products_from>
		<level_products_to>
			<task_tables>
				<task_table>TaskTable_S3A_L0_SR_CAL_06_12.xml</task_table>
			</task_tables>
		</level_products_to>
	</level_products_route>
	
	<level_products_route>
		<level_products_from>
			<acquisition>SR_0_SRA__G</acquisition>
			<satellite_id>A</satellite_id>
		</level_products_from>
		<level_products_to>
			<task_tables>
				<task_table>TaskTable_S3A_L0_SR_SRA_06_12.xml</task_table>
			</task_tables>
		</level_products_to>
	</level_products_route>
	
	<level_products_route>
		<level_products_from>
			<acquisition>TM_0_HKM__G</acquisition>
			<satellite_id>A</satellite_id>
		</level_products_from>
		<level_products_to>
			<task_tables>
				<task_table>TaskTable_S3A_L0_TM_HKM_06_12.xml</task_table>
			</task_tables>
		</level_products_to>
	</level_products_route>
	
	<level_products_route>
		<level_products_from>
			<acquisition>TM_0_HKM2_G</acquisition>
			<satellite_id>A</satellite_id>
		</level_products_from>
		<level_products_to>
			<task_tables>
				<task_table>TaskTable_S3A_L0_TM_HKM2_06_12.xml</task_table>
			</task_tables>
		</level_products_to>
	</level_products_route>
	
	<level_products_route>
		<level_products_from>
			<acquisition>TM_0_NAT__G</acquisition>
			<satellite_id>A</satellite_id>
		</level_products_from>
		<level_products_to>
			<task_tables>
				<task_table>TaskTable_S3A_L0_TM_NAT_06_12.xml</task_table>
			</task_tables>
		</level_products_to>
	</level_products_route>
	
	<!-- Satellite B -->

	<level_products_route>
		<level_products_from>
			<acquisition>DO_0_DOP__G</acquisition>
			<satellite_id>B</satellite_id>
		</level_products_from>
		<level_products_to>
			<task_tables>
				<task_table>TaskTable_S3B_L0_DO_DOP_06_12.xml</task_table>
			</task_tables>
		</level_products_to>
	</level_products_route>
	
	<level_products_route>
		<level_products_from>
			<acquisition>DO_0_NAV__G</acquisition>
			<satellite_id>B</satellite_id>
		</level_products_from>
		<level_products_to>
			<task_tables>
				<task_table>TaskTable_S3B_L0_DO_NAV_06_12.xml</task_table>
			</task_tables>
		</level_products_to>
	</level_products_route>
	
	<level_products_route>
		<level_products_from>
			<acquisition>GN_0_GNS__G</acquisition>
			<satellite_id>B</satellite_id>
		</level_products_from>
		<level_products_to>
			<task_tables>
				<task_table>TaskTable_S3B_L0_GN_GNS_06_12.xml</task_table>
			</task_tables>
		</level_products_to>
	</level_products_route>
	
	<level_products_route>
		<level_products_from>
			<acquisition>MW_0_MWR__G</acquisition>
			<satellite_id>B</satellite_id>
		</level_products_from>
		<level_products_to>
			<task_tables>
				<task_table>TaskTable_S3B_L0_MW_MWR_06_12.xml</task_table>
			</task_tables>
		</level_products_to>
	</level_products_route>
	
	<level_products_route>
		<level_products_from>
			<acquisition>OL_0_CR___G</acquisition>
			<satellite_id>B</satellite_id>
		</level_products_from>
		<level_products_to>
			<task_tables>
				<task_table>TaskTable_S3B_L0_OL_CR__06_12.xml</task_table>
			</task_tables>
		</level_products_to>
	</level_products_route>
	
	<level_products_route>
		<level_products_from>
			<acquisition>OL_0_EFR__G</acquisition>
			<satellite_id>B</satellite_id>
		</level_products_from>
		<level_products_to>
			<task_tables>
				<task_table>TaskTable_S3B_L0_OL_EFR_06_12.xml</task_table>
			</task_tables>
		</level_products_to>
	</level_products_route>
	
	<level_products_route>
		<level_products_from>
			<acquisition>SL_0_SLT__G</acquisition>
			<satellite_id>B</satellite_id>
		</level_products_from>
		<level_products_to>
			<task_tables>
				<task_table>TaskTable_S3B_L0_SL_SLT_06_12.xml</task_table>
			</task_tables>
		</level_products_to>
	</level_products_route>
	
	<level_products_route>
		<level_products_from>
			<acquisition>SR_0_CAL__G</acquisition>
			<satellite_id>B</satellite_id>
		</level_products_from>
		<level_products_to>
			<task_tables>
				<task_table>TaskTable_S3B_L0_SR_CAL_06_12.xml</task_table>
			</task_tables>
		</level_products_to>
	</level_products_route>
	
	<level_products_route>
		<level_products_from>
			<acquisition>SR_0_SRA__G</acquisition>
			<satellite_id>B</satellite_id>
		</level_products_from>
		<level_products_to>
			<task_tables>
				<task_table>TaskTable_S3B_L0_SR_SRA_06_12.xml</task_table>
			</task_tables>
		</level_products_to>
	</level_products_route>
	
	<level_products_route>
		<level_products_from>
			<acquisition>TM_0_HKM__G</acquisition>
			<satellite_id>B</satellite_id>
		</level_products_from>
		<level_products_to>
			<task_tables>
				<task_table>TaskTable_S3B_L0_TM_HKM_06_12.xml</task_table>
			</task_tables>
		</level_products_to>
	</level_products_route>
	
	<level_products_route>
		<level_products_from>
			<acquisition>TM_0_HKM2_G</acquisition>
			<satellite_id>B</satellite_id>
		</level_products_from>
		<level_products_to>
			<task_tables>
				<task_table>TaskTable_S3B_L0_TM_HKM2_06_12.xml</task_table>
			</task_tables>
		</level_products_to>
	</level_products_route>
	
	<level_products_route>
		<level_products_from>
			<acquisition>TM_0_NAT__G</acquisition>
			<satellite_id>B</satellite_id>
		</level_products_from>
		<level_products_to>
			<task_tables>
				<task_table>TaskTable_S3B_L0_TM_NAT_06_12.xml</task_table>
			</task_tables>
		</level_products_to>
	</level_products_route>

</level_products_routing>